ncs_yang/__init__.py
ncs_yang/makefile.py
ncs_yang/ncs_yang.py
ncs_yang/run.py
ncs_yang/utils.py
ncs_yang-1.2.4.3.dist-info/LICENSE
ncs_yang-1.2.4.3.dist-info/METADATA
ncs_yang-1.2.4.3.dist-info/WHEEL
ncs_yang-1.2.4.3.dist-info/entry_points.txt
ncs_yang-1.2.4.3.dist-info/top_level.txt
ncs_yang-1.2.4.3.dist-info/RECORD
